academyruins/__init__.py
academyruins/admin/__init__.py
academyruins/admin/router.py
academyruins/admin/service.py
academyruins/cli_scripts/run.py
academyruins/cr/__init__.py
academyruins/cr/keyword_def.py
academyruins/cr/models.py
academyruins/cr/router.py
academyruins/cr/schemas.py
academyruins/cr/service.py
academyruins/cr/utils.py
academyruins/db.py
academyruins/diffs/__init__.py
academyruins/diffs/models.py
academyruins/diffs/router.py
academyruins/diffs/schemas.py
academyruins/diffs/service.py
academyruins/difftool/__init__.py
academyruins/difftool/diffmaker.py
academyruins/difftool/diffsorter.py
academyruins/difftool/itemdiffer.py
academyruins/difftool/matcher.py
academyruins/difftool/matchscoregraph.py
academyruins/extractor/__init__.py
academyruins/extractor/cr/__init__.py
academyruins/extractor/cr/extract_cr.py
academyruins/extractor/cr/refresh_cr.py
academyruins/extractor/download_doc.py
academyruins/extractor/formatter.py
academyruins/extractor/ipg/__init__.py
academyruins/extractor/ipg/refresh_ipg.py
academyruins/extractor/mtr/__init__.py
academyruins/extractor/mtr/extract_mtr.py
academyruins/extractor/mtr/refresh_mtr.py
academyruins/ipg/__init__.py
academyruins/ipg/models.py
academyruins/ipg/router.py
academyruins/ipg/schemas.py
academyruins/ipg/service.py
academyruins/link/__init__.py
academyruins/link/models.py
academyruins/link/router.py
academyruins/link/service.py
academyruins/main.py
academyruins/models.py
academyruins/mtr/__init__.py
academyruins/mtr/models.py
academyruins/mtr/router.py
academyruins/mtr/schemas.py
academyruins/mtr/service.py
academyruins/openapi/__init__.py
academyruins/openapi/no422.py
academyruins/openapi/openapi_decorators.py
academyruins/openapi/strings.py
academyruins/resources/__init__.py
academyruins/resources/cache.py
academyruins/resources/seeder.py
academyruins/resources/static_paths.py
academyruins/resources/unofficial-glossary.json
academyruins/schemas.py
academyruins/scraper/__init__.py
academyruins-0.5.1.dist-info/LICENSE
academyruins-0.5.1.dist-info/METADATA
academyruins-0.5.1.dist-info/WHEEL
academyruins-0.5.1.dist-info/entry_points.txt
academyruins-0.5.1.dist-info/RECORD
