Metadata-Version: 2.1
Name: academyruins
Version: 0.5.1
Summary: 
Author: Václav Luňák
Author-email:  
Requires-Python: >=3.10,<4.0
Classifier: Programming Language :: Python :: 3
Classifier: Programming Language :: Python :: 3.10
Classifier: Programming Language :: Python :: 3.11
Requires-Dist: APScheduler (>=3.9.1,<4.0.0)
Requires-Dist: SQLAlchemy (>=1.4.41,<2.0.0)
Requires-Dist: alembic (>=1.8.1,<2.0.0)
Requires-Dist: asyncio (>=3.4.3,<4.0.0)
Requires-Dist: beautifulsoup4 (>=4.11.1,<5.0.0)
Requires-Dist: boto3 (>=1.24.84,<2.0.0)
Requires-Dist: fastapi[all] (>=0.103.2,<0.104.0)
Requires-Dist: hjson (>=3.1.0,<4.0.0)
Requires-Dist: logging (>=0.4.9.6,<0.5.0.0)
Requires-Dist: psycopg2-binary (>=2.9.3,<3.0.0)
Requires-Dist: pydantic (>=2.4.2,<3.0.0)
Requires-Dist: requests (>=2.28.1,<3.0.0)
Requires-Dist: thefuzz[speedup] (>=0.19.0,<0.20.0)
Requires-Dist: tika (>=1.24,<2.0)
Requires-Dist: typer[all] (>=0.9.0,<0.10.0)
